cl_convert/__init__.py
cl_convert/convert.py
cl_convert/converters.py
cl_convert/model.py
cl_convert/versions/v0.0.0+2019.01.26.py
cl_convert/versions/v0.0.0+2020.04.16.py
cl_convert/versions/v0.0.0+2020.08.26.py
cl_convert/versions/v0.1.0+2020.09.18.py
cl_convert/versions/v0.1.1+2021.06.11.py
cl_convert/versions/v0.2.0+2021.08.12.py
cl_convert/versions/v0.2.1+2022.03.04.py
cl_export/__init__.py
cl_export/export.py
cl_export/vtk2sitk.py
cell_locator_cli-0.1.0.dist-info/METADATA
cell_locator_cli-0.1.0.dist-info/WHEEL
cell_locator_cli-0.1.0.dist-info/entry_points.txt
cell_locator_cli-0.1.0.dist-info/top_level.txt
cell_locator_cli-0.1.0.dist-info/RECORD
