Metadata-Version: 2.1
Name: cell-locator-cli
Version: 0.1.0
Summary: CLI Tools for Cell Locator
Author-email: David Allemang <david.allemang@kitware.com>, Jean-Christophe Fillion-Robin <jcfr@kitware.com>
License: Slicer License
Project-URL: repository, https://github.com/BICCN/cell-locator
Project-URL: homepage, https://github.com/BICCN/cell-locator/tree/master/Scripts
Project-URL: documentation, https://cell-locator.rtfd.io
Classifier: Development Status :: 4 - Beta
Classifier: Programming Language :: Python :: 3
Classifier: Topic :: Scientific/Engineering :: Medical Science Apps.
Requires-Dist: vtk-addon
Requires-Dist: SimpleITK
